acapi2/__init__.py
acapi2/acquia.py
acapi2/exceptions.py
acapi2/http_request.py
acapi2/version.py
acapi2/resources/__init__.py
acapi2/resources/acquiadata.py
acapi2/resources/acquialist.py
acapi2/resources/acquiaresource.py
acapi2/resources/agreement.py
acapi2/resources/agreementlist.py
acapi2/resources/application.py
acapi2/resources/applicationlist.py
acapi2/resources/environment.py
acapi2/resources/environmentlist.py
acapi2/resources/notification.py
acapi2/resources/notificationlist.py
acapi2/resources/permissionslist.py
acapi2/resources/subscription.py
acapi2/resources/subscriptionlist.py
acapi2/resources/task.py
acapi2/resources/tasklist.py
acapi2/tests/__init__.py
acapi2/tests/basetest.py
acapi2/tests/test_acquia.py
acapi2/tests/test_acquiadata.py
acapi2/tests/test_agreements.py
acapi2/tests/test_applications.py
acapi2/tests/test_environments.py
acapi2/tests/test_http_request.py
acapi2/tests/test_notification.py
acapi2/tests/test_notifications.py
acapi2/tests/test_permissions.py
acapi2/tests/test_subscriptions.py
acapi2/tests/test_tasks.py
acapi2/tests/util.py
acapi2-2.0.4.dist-info/LICENSE.txt
acapi2-2.0.4.dist-info/METADATA
acapi2-2.0.4.dist-info/WHEEL
acapi2-2.0.4.dist-info/top_level.txt
acapi2-2.0.4.dist-info/RECORD
