Metadata-Version: 2.1
Name: acapi2
Version: 2.0.4
Summary: Acquia Cloud API v2 client library.
Home-page: https://github.com/pmatias/python-acquia-cloud-2
Author: Pablo Fabregat
Author-email: pablo@ceruleanhq.com
License: MIT
Download-URL: https://pypi.org/project/acapi2
Platform: any
Classifier: Development Status :: 3 - Alpha
Classifier: Intended Audience :: Developers
Classifier: Intended Audience :: Education
Classifier: License :: OSI Approved :: MIT License
Classifier: Programming Language :: Python
Classifier: Programming Language :: Python :: 3.6
Classifier: Programming Language :: Python :: 3.7
Classifier: Topic :: Internet
Requires-Python: >=3.6
Requires-Dist: backoff (==1.10.0)
Requires-Dist: http-hmac-python (>=2.4.0)
Requires-Dist: requests (>=2.20.0)
Requires-Dist: requests-cache (>=0.5.2)
Requires-Dist: setuptools (>=38.5)
